/*
    Copyright 2005-2006 The Apache Software Foundation or its licensors, as applicable

    Licensed under the Apache License, Version 2.0 (the "License");
    you may not use this file except in compliance with the License.
    You may obtain a copy of the License at

       http://www.apache.org/licenses/LICENSE-2.0

    Unless required by applicable law or agreed to in writing, software
    distributed under the License is distributed on an "AS IS" BASIS,
    WITHOUT WARRANTIES OR CONDITIONS OF ANY KIND, either express or implied.

    See the License for the specific language governing permissions and
    limitations under the License.
*/
/**
 * Generated ccode file
 * @author VMTT (Virtual Machine Testing Tools)
 * @version 1.0
 * @lastmod: Mon Jun 05 15:36:21 NOVST 2006
 */

magic = xCAFEBABE

minor_version = 0

major_version = 46

constant_pool_count = 105

constant_pool {
  /* #1 */ Method = #3 #102
  /* #2 */ Class = #103
  /* #3 */ Class = #104
  /* #4 */ UTF8 = "<init>"
  /* #5 */ UTF8 = "()V"
  /* #6 */ UTF8 = "Code"
  /* #7 */ UTF8 = "LineNumberTable"
  /* #8 */ UTF8 = "test010"
  /* #9 */ UTF8 = "test011"
  /* #10 */ UTF8 = "test012"
  /* #11 */ UTF8 = "test013"
  /* #12 */ UTF8 = "test020"
  /* #13 */ UTF8 = "test021"
  /* #14 */ UTF8 = "test022"
  /* #15 */ UTF8 = "test023"
  /* #16 */ UTF8 = "test024"
  /* #17 */ UTF8 = "test025"
  /* #18 */ UTF8 = "test030"
  /* #19 */ UTF8 = "test031"
  /* #20 */ UTF8 = "test032"
  /* #21 */ UTF8 = "test033"
  /* #22 */ UTF8 = "test040"
  /* #23 */ UTF8 = "test110"
  /* #24 */ UTF8 = "test111"
  /* #25 */ UTF8 = "test112"
  /* #26 */ UTF8 = "test113"
  /* #27 */ UTF8 = "test120"
  /* #28 */ UTF8 = "test121"
  /* #29 */ UTF8 = "test122"
  /* #30 */ UTF8 = "test123"
  /* #31 */ UTF8 = "test124"
  /* #32 */ UTF8 = "test125"
  /* #33 */ UTF8 = "test130"
  /* #34 */ UTF8 = "test131"
  /* #35 */ UTF8 = "test132"
  /* #36 */ UTF8 = "test133"
  /* #37 */ UTF8 = "test140"
  /* #38 */ UTF8 = "test210"
  /* #39 */ UTF8 = "test211"
  /* #40 */ UTF8 = "test212"
  /* #41 */ UTF8 = "test213"
  /* #42 */ UTF8 = "test220"
  /* #43 */ UTF8 = "test221"
  /* #44 */ UTF8 = "test222"
  /* #45 */ UTF8 = "test223"
  /* #46 */ UTF8 = "test224"
  /* #47 */ UTF8 = "test225"
  /* #48 */ UTF8 = "test230"
  /* #49 */ UTF8 = "test231"
  /* #50 */ UTF8 = "test232"
  /* #51 */ UTF8 = "test233"
  /* #52 */ UTF8 = "test240"
  /* #53 */ UTF8 = "teststr010"
  /* #54 */ UTF8 = "teststr011"
  /* #55 */ UTF8 = "teststr012"
  /* #56 */ UTF8 = "teststr013"
  /* #57 */ UTF8 = "teststr020"
  /* #58 */ UTF8 = "teststr021"
  /* #59 */ UTF8 = "teststr022"
  /* #60 */ UTF8 = "teststr023"
  /* #61 */ UTF8 = "teststr024"
  /* #62 */ UTF8 = "teststr025"
  /* #63 */ UTF8 = "teststr030"
  /* #64 */ UTF8 = "teststr031"
  /* #65 */ UTF8 = "teststr032"
  /* #66 */ UTF8 = "teststr033"
  /* #67 */ UTF8 = "teststr040"
  /* #68 */ UTF8 = "teststr110"
  /* #69 */ UTF8 = "teststr111"
  /* #70 */ UTF8 = "teststr112"
  /* #71 */ UTF8 = "teststr113"
  /* #72 */ UTF8 = "teststr120"
  /* #73 */ UTF8 = "teststr121"
  /* #74 */ UTF8 = "teststr122"
  /* #75 */ UTF8 = "teststr123"
  /* #76 */ UTF8 = "teststr124"
  /* #77 */ UTF8 = "teststr125"
  /* #78 */ UTF8 = "teststr130"
  /* #79 */ UTF8 = "teststr131"
  /* #80 */ UTF8 = "teststr132"
  /* #81 */ UTF8 = "teststr133"
  /* #82 */ UTF8 = "teststr140"
  /* #83 */ UTF8 = "teststr210"
  /* #84 */ UTF8 = "teststr211"
  /* #85 */ UTF8 = "teststr212"
  /* #86 */ UTF8 = "teststr213"
  /* #87 */ UTF8 = "teststr220"
  /* #88 */ UTF8 = "teststr221"
  /* #89 */ UTF8 = "teststr222"
  /* #90 */ UTF8 = "teststr223"
  /* #91 */ UTF8 = "teststr224"
  /* #92 */ UTF8 = "teststr225"
  /* #93 */ UTF8 = "teststr230"
  /* #94 */ UTF8 = "teststr231"
  /* #95 */ UTF8 = "teststr232"
  /* #96 */ UTF8 = "teststr233"
  /* #97 */ UTF8 = "teststr240"
  /* #98 */ UTF8 = "testapu"
  /* #99 */ UTF8 = "testapr"
  /* #100 */ UTF8 = "SourceFile"
  /* #101 */ UTF8 = "accessFlags21p.ccode"
  /* #102 */ NameAndType = #4 #5
  /* #103 */ UTF8 = "org/apache/harmony/vts/test/vm/jvms/classFile/methods/accessFlags/accessFlags21/accessFlags21p"
  /* #104 */ UTF8 = "java/lang/Object"
}

access_flags = PUBLIC SUPER ABSTRACT  // x421

this_class = #2  // "Test"

super_class = #3  // "java/lang/Object"

interfaces_count = 0

interfaces {
}

fields_count = 0

methods_count = 93

methods {
  method {
    access_flag = PUBLIC  // x01
    name_index = #4  // "<init>"
    descriptor_index = #5  // "()V"
    attributes_count = 1
      attributes {
        attribute Code {
          attribute_name_index = #6  // "Code"
          attribute_length = 29
          max_stack = 1
          max_locals = 1
          code_length = 5
          code asm {
          0:    aload_0
          1:    invokespecial #1  // "java/lang/Object" "<init>" "()V"
          4:    return
          }
          exception_table_length = 0
          attributes_count = 1
            attributes {
              attribute LineNumberTable {
                attribute_name_index = #7  // "LineNumberTable"
                attribute_length = 6
                line_number_table_length = 1
                line_number_table {
                    // start_pc line_number
                    0 1
                }
              }
            }
        }
      }
  }
  method {
    access_flag = PUBLIC STATIC  // x09
    name_index = #8  // "test010"
    descriptor_index = #5  // "()V"
    attributes_count = 1
      attributes {
        attribute Code {
          attribute_name_index = #6  // "Code"
          attribute_length = 25
          max_stack = 0
          max_locals = 0
          code_length = 1
          code asm {
          0:    return
          }
          exception_table_length = 0
          attributes_count = 1
            attributes {
              attribute LineNumberTable {
                attribute_name_index = #7  // "LineNumberTable"
                attribute_length = 6
                line_number_table_length = 1
                line_number_table {
                    // start_pc line_number
                    0 3
                }
              }
            }
        }
      }
  }
  method {
    access_flag = PUBLIC FINAL  // x11
    name_index = #9  // "test011"
    descriptor_index = #5  // "()V"
    attributes_count = 1
      attributes {
        attribute Code {
          attribute_name_index = #6  // "Code"
          attribute_length = 25
          max_stack = 0
          max_locals = 1
          code_length = 1
          code asm {
          0:    return
          }
          exception_table_length = 0
          attributes_count = 1
            attributes {
              attribute LineNumberTable {
                attribute_name_index = #7  // "LineNumberTable"
                attribute_length = 6
                line_number_table_length = 1
                line_number_table {
                    // start_pc line_number
                    0 5
                }
              }
            }
        }
      }
  }
  method {
    access_flag = PUBLIC SYNCHRONIZED  // x21
    name_index = #10  // "test012"
    descriptor_index = #5  // "()V"
    attributes_count = 1
      attributes {
        attribute Code {
          attribute_name_index = #6  // "Code"
          attribute_length = 25
          max_stack = 0
          max_locals = 1
          code_length = 1
          code asm {
          0:    return
          }
          exception_table_length = 0
          attributes_count = 1
            attributes {
              attribute LineNumberTable {
                attribute_name_index = #7  // "LineNumberTable"
                attribute_length = 6
                line_number_table_length = 1
                line_number_table {
                    // start_pc line_number
                    0 7
                }
              }
            }
        }
      }
  }
  method {
    access_flag = PUBLIC NATIVE  // x101
    name_index = #11  // "test013"
    descriptor_index = #5  // "()V"
    attributes_count = 0
  }
  method {
    access_flag = PUBLIC STATIC FINAL  // x19
    name_index = #12  // "test020"
    descriptor_index = #5  // "()V"
    attributes_count = 1
      attributes {
        attribute Code {
          attribute_name_index = #6  // "Code"
          attribute_length = 25
          max_stack = 0
          max_locals = 0
          code_length = 1
          code asm {
          0:    return
          }
          exception_table_length = 0
          attributes_count = 1
            attributes {
              attribute LineNumberTable {
                attribute_name_index = #7  // "LineNumberTable"
                attribute_length = 6
                line_number_table_length = 1
                line_number_table {
                    // start_pc line_number
                    0 11
                }
              }
            }
        }
      }
  }
  method {
    access_flag = PUBLIC STATIC NATIVE  // x109
    name_index = #13  // "test021"
    descriptor_index = #5  // "()V"
    attributes_count = 0
  }
  method {
    access_flag = PUBLIC STATIC SYNCHRONIZED  // x29
    name_index = #14  // "test022"
    descriptor_index = #5  // "()V"
    attributes_count = 1
      attributes {
        attribute Code {
          attribute_name_index = #6  // "Code"
          attribute_length = 25
          max_stack = 0
          max_locals = 0
          code_length = 1
          code asm {
          0:    return
          }
          exception_table_length = 0
          attributes_count = 1
            attributes {
              attribute LineNumberTable {
                attribute_name_index = #7  // "LineNumberTable"
                attribute_length = 6
                line_number_table_length = 1
                line_number_table {
                    // start_pc line_number
                    0 15
                }
              }
            }
        }
      }
  }
  method {
    access_flag = PUBLIC FINAL NATIVE  // x111
    name_index = #15  // "test023"
    descriptor_index = #5  // "()V"
    attributes_count = 0
  }
  method {
    access_flag = PUBLIC FINAL SYNCHRONIZED  // x31
    name_index = #16  // "test024"
    descriptor_index = #5  // "()V"
    attributes_count = 1
      attributes {
        attribute Code {
          attribute_name_index = #6  // "Code"
          attribute_length = 25
          max_stack = 0
          max_locals = 1
          code_length = 1
          code asm {
          0:    return
          }
          exception_table_length = 0
          attributes_count = 1
            attributes {
              attribute LineNumberTable {
                attribute_name_index = #7  // "LineNumberTable"
                attribute_length = 6
                line_number_table_length = 1
                line_number_table {
                    // start_pc line_number
                    0 19
                }
              }
            }
        }
      }
  }
  method {
    access_flag = PUBLIC SYNCHRONIZED NATIVE  // x121
    name_index = #17  // "test025"
    descriptor_index = #5  // "()V"
    attributes_count = 0
  }
  method {
    access_flag = PUBLIC STATIC FINAL SYNCHRONIZED  // x39
    name_index = #18  // "test030"
    descriptor_index = #5  // "()V"
    attributes_count = 1
      attributes {
        attribute Code {
          attribute_name_index = #6  // "Code"
          attribute_length = 25
          max_stack = 0
          max_locals = 0
          code_length = 1
          code asm {
          0:    return
          }
          exception_table_length = 0
          attributes_count = 1
            attributes {
              attribute LineNumberTable {
                attribute_name_index = #7  // "LineNumberTable"
                attribute_length = 6
                line_number_table_length = 1
                line_number_table {
                    // start_pc line_number
                    0 23
                }
              }
            }
        }
      }
  }
  method {
    access_flag = PUBLIC FINAL SYNCHRONIZED NATIVE  // x131
    name_index = #19  // "test031"
    descriptor_index = #5  // "()V"
    attributes_count = 0
  }
  method {
    access_flag = PUBLIC STATIC FINAL NATIVE  // x119
    name_index = #20  // "test032"
    descriptor_index = #5  // "()V"
    attributes_count = 0
  }
  method {
    access_flag = PUBLIC STATIC SYNCHRONIZED NATIVE  // x129
    name_index = #21  // "test033"
    descriptor_index = #5  // "()V"
    attributes_count = 0
  }
  method {
    access_flag = PUBLIC STATIC FINAL SYNCHRONIZED NATIVE  // x139
    name_index = #22  // "test040"
    descriptor_index = #5  // "()V"
    attributes_count = 0
  }
  method {
    access_flag = PRIVATE NATIVE  // x102
    name_index = #23  // "test110"
    descriptor_index = #5  // "()V"
    attributes_count = 0
  }
  method {
    access_flag = PRIVATE SYNCHRONIZED  // x22
    name_index = #24  // "test111"
    descriptor_index = #5  // "()V"
    attributes_count = 1
      attributes {
        attribute Code {
          attribute_name_index = #6  // "Code"
          attribute_length = 25
          max_stack = 0
          max_locals = 1
          code_length = 1
          code asm {
          0:    return
          }
          exception_table_length = 0
          attributes_count = 1
            attributes {
              attribute LineNumberTable {
                attribute_name_index = #7  // "LineNumberTable"
                attribute_length = 6
                line_number_table_length = 1
                line_number_table {
                    // start_pc line_number
                    0 35
                }
              }
            }
        }
      }
  }
  method {
    access_flag = PRIVATE STATIC  // x0A
    name_index = #25  // "test112"
    descriptor_index = #5  // "()V"
    attributes_count = 1
      attributes {
        attribute Code {
          attribute_name_index = #6  // "Code"
          attribute_length = 25
          max_stack = 0
          max_locals = 0
          code_length = 1
          code asm {
          0:    return
          }
          exception_table_length = 0
          attributes_count = 1
            attributes {
              attribute LineNumberTable {
                attribute_name_index = #7  // "LineNumberTable"
                attribute_length = 6
                line_number_table_length = 1
                line_number_table {
                    // start_pc line_number
                    0 37
                }
              }
            }
        }
      }
  }
  method {
    access_flag = PRIVATE FINAL  // x12
    name_index = #26  // "test113"
    descriptor_index = #5  // "()V"
    attributes_count = 1
      attributes {
        attribute Code {
          attribute_name_index = #6  // "Code"
          attribute_length = 25
          max_stack = 0
          max_locals = 1
          code_length = 1
          code asm {
          0:    return
          }
          exception_table_length = 0
          attributes_count = 1
            attributes {
              attribute LineNumberTable {
                attribute_name_index = #7  // "LineNumberTable"
                attribute_length = 6
                line_number_table_length = 1
                line_number_table {
                    // start_pc line_number
                    0 39
                }
              }
            }
        }
      }
  }
  method {
    access_flag = PRIVATE SYNCHRONIZED NATIVE  // x122
    name_index = #27  // "test120"
    descriptor_index = #5  // "()V"
    attributes_count = 0
  }
  method {
    access_flag = PRIVATE STATIC SYNCHRONIZED  // x2A
    name_index = #28  // "test121"
    descriptor_index = #5  // "()V"
    attributes_count = 1
      attributes {
        attribute Code {
          attribute_name_index = #6  // "Code"
          attribute_length = 25
          max_stack = 0
          max_locals = 0
          code_length = 1
          code asm {
          0:    return
          }
          exception_table_length = 0
          attributes_count = 1
            attributes {
              attribute LineNumberTable {
                attribute_name_index = #7  // "LineNumberTable"
                attribute_length = 6
                line_number_table_length = 1
                line_number_table {
                    // start_pc line_number
                    0 43
                }
              }
            }
        }
      }
  }
  method {
    access_flag = PRIVATE FINAL SYNCHRONIZED  // x32
    name_index = #29  // "test122"
    descriptor_index = #5  // "()V"
    attributes_count = 1
      attributes {
        attribute Code {
          attribute_name_index = #6  // "Code"
          attribute_length = 25
          max_stack = 0
          max_locals = 1
          code_length = 1
          code asm {
          0:    return
          }
          exception_table_length = 0
          attributes_count = 1
            attributes {
              attribute LineNumberTable {
                attribute_name_index = #7  // "LineNumberTable"
                attribute_length = 6
                line_number_table_length = 1
                line_number_table {
                    // start_pc line_number
                    0 45
                }
              }
            }
        }
      }
  }
  method {
    access_flag = PRIVATE STATIC NATIVE  // x10A
    name_index = #30  // "test123"
    descriptor_index = #5  // "()V"
    attributes_count = 0
  }
  method {
    access_flag = PRIVATE FINAL NATIVE  // x112
    name_index = #31  // "test124"
    descriptor_index = #5  // "()V"
    attributes_count = 0
  }
  method {
    access_flag = PRIVATE STATIC FINAL  // x1A
    name_index = #32  // "test125"
    descriptor_index = #5  // "()V"
    attributes_count = 1
      attributes {
        attribute Code {
          attribute_name_index = #6  // "Code"
          attribute_length = 25
          max_stack = 0
          max_locals = 0
          code_length = 1
          code asm {
          0:    return
          }
          exception_table_length = 0
          attributes_count = 1
            attributes {
              attribute LineNumberTable {
                attribute_name_index = #7  // "LineNumberTable"
                attribute_length = 6
                line_number_table_length = 1
                line_number_table {
                    // start_pc line_number
                    0 51
                }
              }
            }
        }
      }
  }
  method {
    access_flag = PRIVATE STATIC FINAL SYNCHRONIZED  // x3A
    name_index = #33  // "test130"
    descriptor_index = #5  // "()V"
    attributes_count = 1
      attributes {
        attribute Code {
          attribute_name_index = #6  // "Code"
          attribute_length = 25
          max_stack = 0
          max_locals = 0
          code_length = 1
          code asm {
          0:    return
          }
          exception_table_length = 0
          attributes_count = 1
            attributes {
              attribute LineNumberTable {
                attribute_name_index = #7  // "LineNumberTable"
                attribute_length = 6
                line_number_table_length = 1
                line_number_table {
                    // start_pc line_number
                    0 53
                }
              }
            }
        }
      }
  }
  method {
    access_flag = PRIVATE STATIC FINAL NATIVE  // x11A
    name_index = #34  // "test131"
    descriptor_index = #5  // "()V"
    attributes_count = 0
  }
  method {
    access_flag = PRIVATE STATIC SYNCHRONIZED NATIVE  // x12A
    name_index = #35  // "test132"
    descriptor_index = #5  // "()V"
    attributes_count = 0
  }
  method {
    access_flag = PRIVATE FINAL SYNCHRONIZED NATIVE  // x132
    name_index = #36  // "test133"
    descriptor_index = #5  // "()V"
    attributes_count = 0
  }
  method {
    access_flag = PRIVATE STATIC FINAL SYNCHRONIZED NATIVE  // x13A
    name_index = #37  // "test140"
    descriptor_index = #5  // "()V"
    attributes_count = 0
  }
  method {
    access_flag = PROTECTED NATIVE  // x104
    name_index = #38  // "test210"
    descriptor_index = #5  // "()V"
    attributes_count = 0
  }
  method {
    access_flag = PROTECTED STATIC  // x0C
    name_index = #39  // "test211"
    descriptor_index = #5  // "()V"
    attributes_count = 1
      attributes {
        attribute Code {
          attribute_name_index = #6  // "Code"
          attribute_length = 25
          max_stack = 0
          max_locals = 0
          code_length = 1
          code asm {
          0:    return
          }
          exception_table_length = 0
          attributes_count = 1
            attributes {
              attribute LineNumberTable {
                attribute_name_index = #7  // "LineNumberTable"
                attribute_length = 6
                line_number_table_length = 1
                line_number_table {
                    // start_pc line_number
                    0 65
                }
              }
            }
        }
      }
  }
  method {
    access_flag = PROTECTED FINAL  // x14
    name_index = #40  // "test212"
    descriptor_index = #5  // "()V"
    attributes_count = 1
      attributes {
        attribute Code {
          attribute_name_index = #6  // "Code"
          attribute_length = 25
          max_stack = 0
          max_locals = 1
          code_length = 1
          code asm {
          0:    return
          }
          exception_table_length = 0
          attributes_count = 1
            attributes {
              attribute LineNumberTable {
                attribute_name_index = #7  // "LineNumberTable"
                attribute_length = 6
                line_number_table_length = 1
                line_number_table {
                    // start_pc line_number
                    0 67
                }
              }
            }
        }
      }
  }
  method {
    access_flag = PROTECTED SYNCHRONIZED  // x24
    name_index = #41  // "test213"
    descriptor_index = #5  // "()V"
    attributes_count = 1
      attributes {
        attribute Code {
          attribute_name_index = #6  // "Code"
          attribute_length = 25
          max_stack = 0
          max_locals = 1
          code_length = 1
          code asm {
          0:    return
          }
          exception_table_length = 0
          attributes_count = 1
            attributes {
              attribute LineNumberTable {
                attribute_name_index = #7  // "LineNumberTable"
                attribute_length = 6
                line_number_table_length = 1
                line_number_table {
                    // start_pc line_number
                    0 69
                }
              }
            }
        }
      }
  }
  method {
    access_flag = PROTECTED SYNCHRONIZED NATIVE  // x124
    name_index = #42  // "test220"
    descriptor_index = #5  // "()V"
    attributes_count = 0
  }
  method {
    access_flag = PROTECTED FINAL NATIVE  // x114
    name_index = #43  // "test221"
    descriptor_index = #5  // "()V"
    attributes_count = 0
  }
  method {
    access_flag = PROTECTED STATIC NATIVE  // x10C
    name_index = #44  // "test222"
    descriptor_index = #5  // "()V"
    attributes_count = 0
  }
  method {
    access_flag = PROTECTED FINAL SYNCHRONIZED  // x34
    name_index = #45  // "test223"
    descriptor_index = #5  // "()V"
    attributes_count = 1
      attributes {
        attribute Code {
          attribute_name_index = #6  // "Code"
          attribute_length = 25
          max_stack = 0
          max_locals = 1
          code_length = 1
          code asm {
          0:    return
          }
          exception_table_length = 0
          attributes_count = 1
            attributes {
              attribute LineNumberTable {
                attribute_name_index = #7  // "LineNumberTable"
                attribute_length = 6
                line_number_table_length = 1
                line_number_table {
                    // start_pc line_number
                    0 77
                }
              }
            }
        }
      }
  }
  method {
    access_flag = PROTECTED STATIC SYNCHRONIZED  // x2C
    name_index = #46  // "test224"
    descriptor_index = #5  // "()V"
    attributes_count = 1
      attributes {
        attribute Code {
          attribute_name_index = #6  // "Code"
          attribute_length = 25
          max_stack = 0
          max_locals = 0
          code_length = 1
          code asm {
          0:    return
          }
          exception_table_length = 0
          attributes_count = 1
            attributes {
              attribute LineNumberTable {
                attribute_name_index = #7  // "LineNumberTable"
                attribute_length = 6
                line_number_table_length = 1
                line_number_table {
                    // start_pc line_number
                    0 79
                }
              }
            }
        }
      }
  }
  method {
    access_flag = PROTECTED STATIC FINAL  // x1C
    name_index = #47  // "test225"
    descriptor_index = #5  // "()V"
    attributes_count = 1
      attributes {
        attribute Code {
          attribute_name_index = #6  // "Code"
          attribute_length = 25
          max_stack = 0
          max_locals = 0
          code_length = 1
          code asm {
          0:    return
          }
          exception_table_length = 0
          attributes_count = 1
            attributes {
              attribute LineNumberTable {
                attribute_name_index = #7  // "LineNumberTable"
                attribute_length = 6
                line_number_table_length = 1
                line_number_table {
                    // start_pc line_number
                    0 81
                }
              }
            }
        }
      }
  }
  method {
    access_flag = PROTECTED STATIC FINAL SYNCHRONIZED  // x3C
    name_index = #48  // "test230"
    descriptor_index = #5  // "()V"
    attributes_count = 1
      attributes {
        attribute Code {
          attribute_name_index = #6  // "Code"
          attribute_length = 25
          max_stack = 0
          max_locals = 0
          code_length = 1
          code asm {
          0:    return
          }
          exception_table_length = 0
          attributes_count = 1
            attributes {
              attribute LineNumberTable {
                attribute_name_index = #7  // "LineNumberTable"
                attribute_length = 6
                line_number_table_length = 1
                line_number_table {
                    // start_pc line_number
                    0 83
                }
              }
            }
        }
      }
  }
  method {
    access_flag = PROTECTED STATIC SYNCHRONIZED NATIVE  // x12C
    name_index = #49  // "test231"
    descriptor_index = #5  // "()V"
    attributes_count = 0
  }
  method {
    access_flag = PROTECTED STATIC FINAL NATIVE  // x11C
    name_index = #50  // "test232"
    descriptor_index = #5  // "()V"
    attributes_count = 0
  }
  method {
    access_flag = PROTECTED FINAL SYNCHRONIZED NATIVE  // x134
    name_index = #51  // "test233"
    descriptor_index = #5  // "()V"
    attributes_count = 0
  }
  method {
    access_flag = PROTECTED STATIC FINAL SYNCHRONIZED NATIVE  // x13C
    name_index = #52  // "test240"
    descriptor_index = #5  // "()V"
    attributes_count = 0
  }
  method {
    access_flag = PUBLIC SYNCHRONIZED  // x21
    name_index = #53  // "teststr010"
    descriptor_index = #5  // "()V"
    attributes_count = 1
      attributes {
        attribute Code {
          attribute_name_index = #6  // "Code"
          attribute_length = 25
          max_stack = 0
          max_locals = 1
          code_length = 1
          code asm {
          0:    return
          }
          exception_table_length = 0
          attributes_count = 1
            attributes {
              attribute LineNumberTable {
                attribute_name_index = #7  // "LineNumberTable"
                attribute_length = 6
                line_number_table_length = 1
                line_number_table {
                    // start_pc line_number
                    0 93
                }
              }
            }
        }
      }
  }
  method {
    access_flag = PUBLIC STATIC  // x09
    name_index = #54  // "teststr011"
    descriptor_index = #5  // "()V"
    attributes_count = 1
      attributes {
        attribute Code {
          attribute_name_index = #6  // "Code"
          attribute_length = 25
          max_stack = 0
          max_locals = 0
          code_length = 1
          code asm {
          0:    return
          }
          exception_table_length = 0
          attributes_count = 1
            attributes {
              attribute LineNumberTable {
                attribute_name_index = #7  // "LineNumberTable"
                attribute_length = 6
                line_number_table_length = 1
                line_number_table {
                    // start_pc line_number
                    0 95
                }
              }
            }
        }
      }
  }
  method {
    access_flag = PUBLIC FINAL  // x11
    name_index = #55  // "teststr012"
    descriptor_index = #5  // "()V"
    attributes_count = 1
      attributes {
        attribute Code {
          attribute_name_index = #6  // "Code"
          attribute_length = 25
          max_stack = 0
          max_locals = 1
          code_length = 1
          code asm {
          0:    return
          }
          exception_table_length = 0
          attributes_count = 1
            attributes {
              attribute LineNumberTable {
                attribute_name_index = #7  // "LineNumberTable"
                attribute_length = 6
                line_number_table_length = 1
                line_number_table {
                    // start_pc line_number
                    0 97
                }
              }
            }
        }
      }
  }
  method {
    access_flag = PUBLIC STRICT  // x801
    name_index = #56  // "teststr013"
    descriptor_index = #5  // "()V"
    attributes_count = 1
      attributes {
        attribute Code {
          attribute_name_index = #6  // "Code"
          attribute_length = 25
          max_stack = 0
          max_locals = 1
          code_length = 1
          code asm {
          0:    return
          }
          exception_table_length = 0
          attributes_count = 1
            attributes {
              attribute LineNumberTable {
                attribute_name_index = #7  // "LineNumberTable"
                attribute_length = 6
                line_number_table_length = 1
                line_number_table {
                    // start_pc line_number
                    0 99
                }
              }
            }
        }
      }
  }
  method {
    access_flag = PUBLIC SYNCHRONIZED STRICT  // x821
    name_index = #57  // "teststr020"
    descriptor_index = #5  // "()V"
    attributes_count = 1
      attributes {
        attribute Code {
          attribute_name_index = #6  // "Code"
          attribute_length = 25
          max_stack = 0
          max_locals = 1
          code_length = 1
          code asm {
          0:    return
          }
          exception_table_length = 0
          attributes_count = 1
            attributes {
              attribute LineNumberTable {
                attribute_name_index = #7  // "LineNumberTable"
                attribute_length = 6
                line_number_table_length = 1
                line_number_table {
                    // start_pc line_number
                    0 101
                }
              }
            }
        }
      }
  }
  method {
    access_flag = PUBLIC STATIC SYNCHRONIZED  // x29
    name_index = #58  // "teststr021"
    descriptor_index = #5  // "()V"
    attributes_count = 1
      attributes {
        attribute Code {
          attribute_name_index = #6  // "Code"
          attribute_length = 25
          max_stack = 0
          max_locals = 0
          code_length = 1
          code asm {
          0:    return
          }
          exception_table_length = 0
          attributes_count = 1
            attributes {
              attribute LineNumberTable {
                attribute_name_index = #7  // "LineNumberTable"
                attribute_length = 6
                line_number_table_length = 1
                line_number_table {
                    // start_pc line_number
                    0 103
                }
              }
            }
        }
      }
  }
  method {
    access_flag = PUBLIC FINAL SYNCHRONIZED  // x31
    name_index = #59  // "teststr022"
    descriptor_index = #5  // "()V"
    attributes_count = 1
      attributes {
        attribute Code {
          attribute_name_index = #6  // "Code"
          attribute_length = 25
          max_stack = 0
          max_locals = 1
          code_length = 1
          code asm {
          0:    return
          }
          exception_table_length = 0
          attributes_count = 1
            attributes {
              attribute LineNumberTable {
                attribute_name_index = #7  // "LineNumberTable"
                attribute_length = 6
                line_number_table_length = 1
                line_number_table {
                    // start_pc line_number
                    0 105
                }
              }
            }
        }
      }
  }
  method {
    access_flag = PUBLIC STATIC STRICT  // x809
    name_index = #60  // "teststr023"
    descriptor_index = #5  // "()V"
    attributes_count = 1
      attributes {
        attribute Code {
          attribute_name_index = #6  // "Code"
          attribute_length = 25
          max_stack = 0
          max_locals = 0
          code_length = 1
          code asm {
          0:    return
          }
          exception_table_length = 0
          attributes_count = 1
            attributes {
              attribute LineNumberTable {
                attribute_name_index = #7  // "LineNumberTable"
                attribute_length = 6
                line_number_table_length = 1
                line_number_table {
                    // start_pc line_number
                    0 107
                }
              }
            }
        }
      }
  }
  method {
    access_flag = PUBLIC FINAL STRICT  // x811
    name_index = #61  // "teststr024"
    descriptor_index = #5  // "()V"
    attributes_count = 1
      attributes {
        attribute Code {
          attribute_name_index = #6  // "Code"
          attribute_length = 25
          max_stack = 0
          max_locals = 1
          code_length = 1
          code asm {
          0:    return
          }
          exception_table_length = 0
          attributes_count = 1
            attributes {
              attribute LineNumberTable {
                attribute_name_index = #7  // "LineNumberTable"
                attribute_length = 6
                line_number_table_length = 1
                line_number_table {
                    // start_pc line_number
                    0 109
                }
              }
            }
        }
      }
  }
  method {
    access_flag = PUBLIC STATIC FINAL  // x19
    name_index = #62  // "teststr025"
    descriptor_index = #5  // "()V"
    attributes_count = 1
      attributes {
        attribute Code {
          attribute_name_index = #6  // "Code"
          attribute_length = 25
          max_stack = 0
          max_locals = 0
          code_length = 1
          code asm {
          0:    return
          }
          exception_table_length = 0
          attributes_count = 1
            attributes {
              attribute LineNumberTable {
                attribute_name_index = #7  // "LineNumberTable"
                attribute_length = 6
                line_number_table_length = 1
                line_number_table {
                    // start_pc line_number
                    0 111
                }
              }
            }
        }
      }
  }
  method {
    access_flag = PUBLIC STATIC FINAL SYNCHRONIZED  // x39
    name_index = #63  // "teststr030"
    descriptor_index = #5  // "()V"
    attributes_count = 1
      attributes {
        attribute Code {
          attribute_name_index = #6  // "Code"
          attribute_length = 25
          max_stack = 0
          max_locals = 0
          code_length = 1
          code asm {
          0:    return
          }
          exception_table_length = 0
          attributes_count = 1
            attributes {
              attribute LineNumberTable {
                attribute_name_index = #7  // "LineNumberTable"
                attribute_length = 6
                line_number_table_length = 1
                line_number_table {
                    // start_pc line_number
                    0 113
                }
              }
            }
        }
      }
  }
  method {
    access_flag = PUBLIC STATIC SYNCHRONIZED STRICT  // x829
    name_index = #64  // "teststr031"
    descriptor_index = #5  // "()V"
    attributes_count = 1
      attributes {
        attribute Code {
          attribute_name_index = #6  // "Code"
          attribute_length = 25
          max_stack = 0
          max_locals = 0
          code_length = 1
          code asm {
          0:    return
          }
          exception_table_length = 0
          attributes_count = 1
            attributes {
              attribute LineNumberTable {
                attribute_name_index = #7  // "LineNumberTable"
                attribute_length = 6
                line_number_table_length = 1
                line_number_table {
                    // start_pc line_number
                    0 115
                }
              }
            }
        }
      }
  }
  method {
    access_flag = PUBLIC STATIC FINAL STRICT  // x819
    name_index = #65  // "teststr032"
    descriptor_index = #5  // "()V"
    attributes_count = 1
      attributes {
        attribute Code {
          attribute_name_index = #6  // "Code"
          attribute_length = 25
          max_stack = 0
          max_locals = 0
          code_length = 1
          code asm {
          0:    return
          }
          exception_table_length = 0
          attributes_count = 1
            attributes {
              attribute LineNumberTable {
                attribute_name_index = #7  // "LineNumberTable"
                attribute_length = 6
                line_number_table_length = 1
                line_number_table {
                    // start_pc line_number
                    0 117
                }
              }
            }
        }
      }
  }
  method {
    access_flag = PUBLIC FINAL SYNCHRONIZED STRICT  // x831
    name_index = #66  // "teststr033"
    descriptor_index = #5  // "()V"
    attributes_count = 1
      attributes {
        attribute Code {
          attribute_name_index = #6  // "Code"
          attribute_length = 25
          max_stack = 0
          max_locals = 1
          code_length = 1
          code asm {
          0:    return
          }
          exception_table_length = 0
          attributes_count = 1
            attributes {
              attribute LineNumberTable {
                attribute_name_index = #7  // "LineNumberTable"
                attribute_length = 6
                line_number_table_length = 1
                line_number_table {
                    // start_pc line_number
                    0 119
                }
              }
            }
        }
      }
  }
  method {
    access_flag = PUBLIC STATIC FINAL SYNCHRONIZED STRICT  // x839
    name_index = #67  // "teststr040"
    descriptor_index = #5  // "()V"
    attributes_count = 1
      attributes {
        attribute Code {
          attribute_name_index = #6  // "Code"
          attribute_length = 25
          max_stack = 0
          max_locals = 0
          code_length = 1
          code asm {
          0:    return
          }
          exception_table_length = 0
          attributes_count = 1
            attributes {
              attribute LineNumberTable {
                attribute_name_index = #7  // "LineNumberTable"
                attribute_length = 6
                line_number_table_length = 1
                line_number_table {
                    // start_pc line_number
                    0 121
                }
              }
            }
        }
      }
  }
  method {
    access_flag = PRIVATE STATIC  // x0A
    name_index = #68  // "teststr110"
    descriptor_index = #5  // "()V"
    attributes_count = 1
      attributes {
        attribute Code {
          attribute_name_index = #6  // "Code"
          attribute_length = 25
          max_stack = 0
          max_locals = 0
          code_length = 1
          code asm {
          0:    return
          }
          exception_table_length = 0
          attributes_count = 1
            attributes {
              attribute LineNumberTable {
                attribute_name_index = #7  // "LineNumberTable"
                attribute_length = 6
                line_number_table_length = 1
                line_number_table {
                    // start_pc line_number
                    0 123
                }
              }
            }
        }
      }
  }
  method {
    access_flag = PRIVATE STRICT  // x802
    name_index = #69  // "teststr111"
    descriptor_index = #5  // "()V"
    attributes_count = 1
      attributes {
        attribute Code {
          attribute_name_index = #6  // "Code"
          attribute_length = 25
          max_stack = 0
          max_locals = 1
          code_length = 1
          code asm {
          0:    return
          }
          exception_table_length = 0
          attributes_count = 1
            attributes {
              attribute LineNumberTable {
                attribute_name_index = #7  // "LineNumberTable"
                attribute_length = 6
                line_number_table_length = 1
                line_number_table {
                    // start_pc line_number
                    0 125
                }
              }
            }
        }
      }
  }
  method {
    access_flag = PRIVATE SYNCHRONIZED  // x22
    name_index = #70  // "teststr112"
    descriptor_index = #5  // "()V"
    attributes_count = 1
      attributes {
        attribute Code {
          attribute_name_index = #6  // "Code"
          attribute_length = 25
          max_stack = 0
          max_locals = 1
          code_length = 1
          code asm {
          0:    return
          }
          exception_table_length = 0
          attributes_count = 1
            attributes {
              attribute LineNumberTable {
                attribute_name_index = #7  // "LineNumberTable"
                attribute_length = 6
                line_number_table_length = 1
                line_number_table {
                    // start_pc line_number
                    0 127
                }
              }
            }
        }
      }
  }
  method {
    access_flag = PRIVATE FINAL  // x12
    name_index = #71  // "teststr113"
    descriptor_index = #5  // "()V"
    attributes_count = 1
      attributes {
        attribute Code {
          attribute_name_index = #6  // "Code"
          attribute_length = 25
          max_stack = 0
          max_locals = 1
          code_length = 1
          code asm {
          0:    return
          }
          exception_table_length = 0
          attributes_count = 1
            attributes {
              attribute LineNumberTable {
                attribute_name_index = #7  // "LineNumberTable"
                attribute_length = 6
                line_number_table_length = 1
                line_number_table {
                    // start_pc line_number
                    0 129
                }
              }
            }
        }
      }
  }
  method {
    access_flag = PRIVATE FINAL STRICT  // x812
    name_index = #72  // "teststr120"
    descriptor_index = #5  // "()V"
    attributes_count = 1
      attributes {
        attribute Code {
          attribute_name_index = #6  // "Code"
          attribute_length = 25
          max_stack = 0
          max_locals = 1
          code_length = 1
          code asm {
          0:    return
          }
          exception_table_length = 0
          attributes_count = 1
            attributes {
              attribute LineNumberTable {
                attribute_name_index = #7  // "LineNumberTable"
                attribute_length = 6
                line_number_table_length = 1
                line_number_table {
                    // start_pc line_number
                    0 131
                }
              }
            }
        }
      }
  }
  method {
    access_flag = PRIVATE FINAL SYNCHRONIZED  // x32
    name_index = #73  // "teststr121"
    descriptor_index = #5  // "()V"
    attributes_count = 1
      attributes {
        attribute Code {
          attribute_name_index = #6  // "Code"
          attribute_length = 25
          max_stack = 0
          max_locals = 1
          code_length = 1
          code asm {
          0:    return
          }
          exception_table_length = 0
          attributes_count = 1
            attributes {
              attribute LineNumberTable {
                attribute_name_index = #7  // "LineNumberTable"
                attribute_length = 6
                line_number_table_length = 1
                line_number_table {
                    // start_pc line_number
                    0 133
                }
              }
            }
        }
      }
  }
  method {
    access_flag = PRIVATE STATIC FINAL  // x1A
    name_index = #74  // "teststr122"
    descriptor_index = #5  // "()V"
    attributes_count = 1
      attributes {
        attribute Code {
          attribute_name_index = #6  // "Code"
          attribute_length = 25
          max_stack = 0
          max_locals = 0
          code_length = 1
          code asm {
          0:    return
          }
          exception_table_length = 0
          attributes_count = 1
            attributes {
              attribute LineNumberTable {
                attribute_name_index = #7  // "LineNumberTable"
                attribute_length = 6
                line_number_table_length = 1
                line_number_table {
                    // start_pc line_number
                    0 135
                }
              }
            }
        }
      }
  }
  method {
    access_flag = PRIVATE SYNCHRONIZED STRICT  // x822
    name_index = #75  // "teststr123"
    descriptor_index = #5  // "()V"
    attributes_count = 1
      attributes {
        attribute Code {
          attribute_name_index = #6  // "Code"
          attribute_length = 25
          max_stack = 0
          max_locals = 1
          code_length = 1
          code asm {
          0:    return
          }
          exception_table_length = 0
          attributes_count = 1
            attributes {
              attribute LineNumberTable {
                attribute_name_index = #7  // "LineNumberTable"
                attribute_length = 6
                line_number_table_length = 1
                line_number_table {
                    // start_pc line_number
                    0 137
                }
              }
            }
        }
      }
  }
  method {
    access_flag = PRIVATE STATIC STRICT  // x80A
    name_index = #76  // "teststr124"
    descriptor_index = #5  // "()V"
    attributes_count = 1
      attributes {
        attribute Code {
          attribute_name_index = #6  // "Code"
          attribute_length = 25
          max_stack = 0
          max_locals = 0
          code_length = 1
          code asm {
          0:    return
          }
          exception_table_length = 0
          attributes_count = 1
            attributes {
              attribute LineNumberTable {
                attribute_name_index = #7  // "LineNumberTable"
                attribute_length = 6
                line_number_table_length = 1
                line_number_table {
                    // start_pc line_number
                    0 139
                }
              }
            }
        }
      }
  }
  method {
    access_flag = PRIVATE STATIC SYNCHRONIZED  // x2A
    name_index = #77  // "teststr125"
    descriptor_index = #5  // "()V"
    attributes_count = 1
      attributes {
        attribute Code {
          attribute_name_index = #6  // "Code"
          attribute_length = 25
          max_stack = 0
          max_locals = 0
          code_length = 1
          code asm {
          0:    return
          }
          exception_table_length = 0
          attributes_count = 1
            attributes {
              attribute LineNumberTable {
                attribute_name_index = #7  // "LineNumberTable"
                attribute_length = 6
                line_number_table_length = 1
                line_number_table {
                    // start_pc line_number
                    0 141
                }
              }
            }
        }
      }
  }
  method {
    access_flag = PRIVATE STATIC SYNCHRONIZED STRICT  // x82A
    name_index = #78  // "teststr130"
    descriptor_index = #5  // "()V"
    attributes_count = 1
      attributes {
        attribute Code {
          attribute_name_index = #6  // "Code"
          attribute_length = 25
          max_stack = 0
          max_locals = 0
          code_length = 1
          code asm {
          0:    return
          }
          exception_table_length = 0
          attributes_count = 1
            attributes {
              attribute LineNumberTable {
                attribute_name_index = #7  // "LineNumberTable"
                attribute_length = 6
                line_number_table_length = 1
                line_number_table {
                    // start_pc line_number
                    0 143
                }
              }
            }
        }
      }
  }
  method {
    access_flag = PRIVATE FINAL SYNCHRONIZED STRICT  // x832
    name_index = #79  // "teststr131"
    descriptor_index = #5  // "()V"
    attributes_count = 1
      attributes {
        attribute Code {
          attribute_name_index = #6  // "Code"
          attribute_length = 25
          max_stack = 0
          max_locals = 1
          code_length = 1
          code asm {
          0:    return
          }
          exception_table_length = 0
          attributes_count = 1
            attributes {
              attribute LineNumberTable {
                attribute_name_index = #7  // "LineNumberTable"
                attribute_length = 6
                line_number_table_length = 1
                line_number_table {
                    // start_pc line_number
                    0 145
                }
              }
            }
        }
      }
  }
  method {
    access_flag = PRIVATE STATIC FINAL STRICT  // x81A
    name_index = #80  // "teststr132"
    descriptor_index = #5  // "()V"
    attributes_count = 1
      attributes {
        attribute Code {
          attribute_name_index = #6  // "Code"
          attribute_length = 25
          max_stack = 0
          max_locals = 0
          code_length = 1
          code asm {
          0:    return
          }
          exception_table_length = 0
          attributes_count = 1
            attributes {
              attribute LineNumberTable {
                attribute_name_index = #7  // "LineNumberTable"
                attribute_length = 6
                line_number_table_length = 1
                line_number_table {
                    // start_pc line_number
                    0 147
                }
              }
            }
        }
      }
  }
  method {
    access_flag = PRIVATE STATIC FINAL SYNCHRONIZED  // x3A
    name_index = #81  // "teststr133"
    descriptor_index = #5  // "()V"
    attributes_count = 1
      attributes {
        attribute Code {
          attribute_name_index = #6  // "Code"
          attribute_length = 25
          max_stack = 0
          max_locals = 0
          code_length = 1
          code asm {
          0:    return
          }
          exception_table_length = 0
          attributes_count = 1
            attributes {
              attribute LineNumberTable {
                attribute_name_index = #7  // "LineNumberTable"
                attribute_length = 6
                line_number_table_length = 1
                line_number_table {
                    // start_pc line_number
                    0 149
                }
              }
            }
        }
      }
  }
  method {
    access_flag = PRIVATE STATIC FINAL SYNCHRONIZED STRICT  // x83A
    name_index = #82  // "teststr140"
    descriptor_index = #5  // "()V"
    attributes_count = 1
      attributes {
        attribute Code {
          attribute_name_index = #6  // "Code"
          attribute_length = 25
          max_stack = 0
          max_locals = 0
          code_length = 1
          code asm {
          0:    return
          }
          exception_table_length = 0
          attributes_count = 1
            attributes {
              attribute LineNumberTable {
                attribute_name_index = #7  // "LineNumberTable"
                attribute_length = 6
                line_number_table_length = 1
                line_number_table {
                    // start_pc line_number
                    0 151
                }
              }
            }
        }
      }
  }
  method {
    access_flag = PROTECTED STRICT  // x804
    name_index = #83  // "teststr210"
    descriptor_index = #5  // "()V"
    attributes_count = 1
      attributes {
        attribute Code {
          attribute_name_index = #6  // "Code"
          attribute_length = 25
          max_stack = 0
          max_locals = 1
          code_length = 1
          code asm {
          0:    return
          }
          exception_table_length = 0
          attributes_count = 1
            attributes {
              attribute LineNumberTable {
                attribute_name_index = #7  // "LineNumberTable"
                attribute_length = 6
                line_number_table_length = 1
                line_number_table {
                    // start_pc line_number
                    0 153
                }
              }
            }
        }
      }
  }
  method {
    access_flag = PROTECTED STATIC  // x0C
    name_index = #84  // "teststr211"
    descriptor_index = #5  // "()V"
    attributes_count = 1
      attributes {
        attribute Code {
          attribute_name_index = #6  // "Code"
          attribute_length = 25
          max_stack = 0
          max_locals = 0
          code_length = 1
          code asm {
          0:    return
          }
          exception_table_length = 0
          attributes_count = 1
            attributes {
              attribute LineNumberTable {
                attribute_name_index = #7  // "LineNumberTable"
                attribute_length = 6
                line_number_table_length = 1
                line_number_table {
                    // start_pc line_number
                    0 155
                }
              }
            }
        }
      }
  }
  method {
    access_flag = PROTECTED FINAL  // x14
    name_index = #85  // "teststr212"
    descriptor_index = #5  // "()V"
    attributes_count = 1
      attributes {
        attribute Code {
          attribute_name_index = #6  // "Code"
          attribute_length = 25
          max_stack = 0
          max_locals = 1
          code_length = 1
          code asm {
          0:    return
          }
          exception_table_length = 0
          attributes_count = 1
            attributes {
              attribute LineNumberTable {
                attribute_name_index = #7  // "LineNumberTable"
                attribute_length = 6
                line_number_table_length = 1
                line_number_table {
                    // start_pc line_number
                    0 157
                }
              }
            }
        }
      }
  }
  method {
    access_flag = PROTECTED SYNCHRONIZED  // x24
    name_index = #86  // "teststr213"
    descriptor_index = #5  // "()V"
    attributes_count = 1
      attributes {
        attribute Code {
          attribute_name_index = #6  // "Code"
          attribute_length = 25
          max_stack = 0
          max_locals = 1
          code_length = 1
          code asm {
          0:    return
          }
          exception_table_length = 0
          attributes_count = 1
            attributes {
              attribute LineNumberTable {
                attribute_name_index = #7  // "LineNumberTable"
                attribute_length = 6
                line_number_table_length = 1
                line_number_table {
                    // start_pc line_number
                    0 159
                }
              }
            }
        }
      }
  }
  method {
    access_flag = PROTECTED SYNCHRONIZED STRICT  // x824
    name_index = #87  // "teststr220"
    descriptor_index = #5  // "()V"
    attributes_count = 1
      attributes {
        attribute Code {
          attribute_name_index = #6  // "Code"
          attribute_length = 25
          max_stack = 0
          max_locals = 1
          code_length = 1
          code asm {
          0:    return
          }
          exception_table_length = 0
          attributes_count = 1
            attributes {
              attribute LineNumberTable {
                attribute_name_index = #7  // "LineNumberTable"
                attribute_length = 6
                line_number_table_length = 1
                line_number_table {
                    // start_pc line_number
                    0 161
                }
              }
            }
        }
      }
  }
  method {
    access_flag = PROTECTED STATIC SYNCHRONIZED  // x2C
    name_index = #88  // "teststr221"
    descriptor_index = #5  // "()V"
    attributes_count = 1
      attributes {
        attribute Code {
          attribute_name_index = #6  // "Code"
          attribute_length = 25
          max_stack = 0
          max_locals = 0
          code_length = 1
          code asm {
          0:    return
          }
          exception_table_length = 0
          attributes_count = 1
            attributes {
              attribute LineNumberTable {
                attribute_name_index = #7  // "LineNumberTable"
                attribute_length = 6
                line_number_table_length = 1
                line_number_table {
                    // start_pc line_number
                    0 163
                }
              }
            }
        }
      }
  }
  method {
    access_flag = PROTECTED FINAL SYNCHRONIZED  // x34
    name_index = #89  // "teststr222"
    descriptor_index = #5  // "()V"
    attributes_count = 1
      attributes {
        attribute Code {
          attribute_name_index = #6  // "Code"
          attribute_length = 25
          max_stack = 0
          max_locals = 1
          code_length = 1
          code asm {
          0:    return
          }
          exception_table_length = 0
          attributes_count = 1
            attributes {
              attribute LineNumberTable {
                attribute_name_index = #7  // "LineNumberTable"
                attribute_length = 6
                line_number_table_length = 1
                line_number_table {
                    // start_pc line_number
                    0 165
                }
              }
            }
        }
      }
  }
  method {
    access_flag = PROTECTED STATIC STRICT  // x80C
    name_index = #90  // "teststr223"
    descriptor_index = #5  // "()V"
    attributes_count = 1
      attributes {
        attribute Code {
          attribute_name_index = #6  // "Code"
          attribute_length = 25
          max_stack = 0
          max_locals = 0
          code_length = 1
          code asm {
          0:    return
          }
          exception_table_length = 0
          attributes_count = 1
            attributes {
              attribute LineNumberTable {
                attribute_name_index = #7  // "LineNumberTable"
                attribute_length = 6
                line_number_table_length = 1
                line_number_table {
                    // start_pc line_number
                    0 167
                }
              }
            }
        }
      }
  }
  method {
    access_flag = PROTECTED FINAL STRICT  // x814
    name_index = #91  // "teststr224"
    descriptor_index = #5  // "()V"
    attributes_count = 1
      attributes {
        attribute Code {
          attribute_name_index = #6  // "Code"
          attribute_length = 25
          max_stack = 0
          max_locals = 1
          code_length = 1
          code asm {
          0:    return
          }
          exception_table_length = 0
          attributes_count = 1
            attributes {
              attribute LineNumberTable {
                attribute_name_index = #7  // "LineNumberTable"
                attribute_length = 6
                line_number_table_length = 1
                line_number_table {
                    // start_pc line_number
                    0 169
                }
              }
            }
        }
      }
  }
  method {
    access_flag = PROTECTED STATIC FINAL  // x1C
    name_index = #92  // "teststr225"
    descriptor_index = #5  // "()V"
    attributes_count = 1
      attributes {
        attribute Code {
          attribute_name_index = #6  // "Code"
          attribute_length = 25
          max_stack = 0
          max_locals = 0
          code_length = 1
          code asm {
          0:    return
          }
          exception_table_length = 0
          attributes_count = 1
            attributes {
              attribute LineNumberTable {
                attribute_name_index = #7  // "LineNumberTable"
                attribute_length = 6
                line_number_table_length = 1
                line_number_table {
                    // start_pc line_number
                    0 171
                }
              }
            }
        }
      }
  }
  method {
    access_flag = PROTECTED STATIC FINAL STRICT  // x81C
    name_index = #93  // "teststr230"
    descriptor_index = #5  // "()V"
    attributes_count = 1
      attributes {
        attribute Code {
          attribute_name_index = #6  // "Code"
          attribute_length = 25
          max_stack = 0
          max_locals = 0
          code_length = 1
          code asm {
          0:    return
          }
          exception_table_length = 0
          attributes_count = 1
            attributes {
              attribute LineNumberTable {
                attribute_name_index = #7  // "LineNumberTable"
                attribute_length = 6
                line_number_table_length = 1
                line_number_table {
                    // start_pc line_number
                    0 173
                }
              }
            }
        }
      }
  }
  method {
    access_flag = PROTECTED STATIC FINAL SYNCHRONIZED  // x3C
    name_index = #94  // "teststr231"
    descriptor_index = #5  // "()V"
    attributes_count = 1
      attributes {
        attribute Code {
          attribute_name_index = #6  // "Code"
          attribute_length = 25
          max_stack = 0
          max_locals = 0
          code_length = 1
          code asm {
          0:    return
          }
          exception_table_length = 0
          attributes_count = 1
            attributes {
              attribute LineNumberTable {
                attribute_name_index = #7  // "LineNumberTable"
                attribute_length = 6
                line_number_table_length = 1
                line_number_table {
                    // start_pc line_number
                    0 175
                }
              }
            }
        }
      }
  }
  method {
    access_flag = PROTECTED STATIC SYNCHRONIZED STRICT  // x82C
    name_index = #95  // "teststr232"
    descriptor_index = #5  // "()V"
    attributes_count = 1
      attributes {
        attribute Code {
          attribute_name_index = #6  // "Code"
          attribute_length = 25
          max_stack = 0
          max_locals = 0
          code_length = 1
          code asm {
          0:    return
          }
          exception_table_length = 0
          attributes_count = 1
            attributes {
              attribute LineNumberTable {
                attribute_name_index = #7  // "LineNumberTable"
                attribute_length = 6
                line_number_table_length = 1
                line_number_table {
                    // start_pc line_number
                    0 177
                }
              }
            }
        }
      }
  }
  method {
    access_flag = PROTECTED FINAL SYNCHRONIZED STRICT  // x834
    name_index = #96  // "teststr233"
    descriptor_index = #5  // "()V"
    attributes_count = 1
      attributes {
        attribute Code {
          attribute_name_index = #6  // "Code"
          attribute_length = 25
          max_stack = 0
          max_locals = 1
          code_length = 1
          code asm {
          0:    return
          }
          exception_table_length = 0
          attributes_count = 1
            attributes {
              attribute LineNumberTable {
                attribute_name_index = #7  // "LineNumberTable"
                attribute_length = 6
                line_number_table_length = 1
                line_number_table {
                    // start_pc line_number
                    0 179
                }
              }
            }
        }
      }
  }
  method {
    access_flag = PROTECTED STATIC FINAL SYNCHRONIZED STRICT  // x83C
    name_index = #97  // "teststr240"
    descriptor_index = #5  // "()V"
    attributes_count = 1
      attributes {
        attribute Code {
          attribute_name_index = #6  // "Code"
          attribute_length = 25
          max_stack = 0
          max_locals = 0
          code_length = 1
          code asm {
          0:    return
          }
          exception_table_length = 0
          attributes_count = 1
            attributes {
              attribute LineNumberTable {
                attribute_name_index = #7  // "LineNumberTable"
                attribute_length = 6
                line_number_table_length = 1
                line_number_table {
                    // start_pc line_number
                    0 181
                }
              }
            }
        }
      }
  }
  method {
    access_flag = PUBLIC ABSTRACT  // x401
    name_index = #98  // "testapu"
    descriptor_index = #5  // "()V"
    attributes_count = 0
  }
  method {
    access_flag = PROTECTED ABSTRACT  // x404
    name_index = #99  // "testapr"
    descriptor_index = #5  // "()V"
    attributes_count = 0
  }
}

attributes_count = 1
attributes {
  attribute SourceFile {
    attribute_name_index = #100  // "SourceFile"
    attribute_length = 2
    sourcefile_index = #101  // "accessFlags21p.ccode"
  }
}
