/*
    Copyright 2005-2006 The Apache Software Foundation or its licensors, as applicable

    Licensed under the Apache License, Version 2.0 (the "License");
    you may not use this file except in compliance with the License.
    You may obtain a copy of the License at

       http://www.apache.org/licenses/LICENSE-2.0

    Unless required by applicable law or agreed to in writing, software
    distributed under the License is distributed on an "AS IS" BASIS,
    WITHOUT WARRANTIES OR CONDITIONS OF ANY KIND, either express or implied.

    See the License for the specific language governing permissions and
    limitations under the License.
*/
// Ccode file

/**
 * @author: Khen G. Kim
 * @version: $Revision: 1.4 $
 */

magic = xCAFEBABE

minor_version = 0

major_version = 46

constant_pool_count = 39

constant_pool {
  /* #1 */ Method = #10 #20
  /* #2 */ String = #21
  /* #3 */ Field = #4 #22
  /* #4 */ Class = #23
  /* #5 */ Method = #4 #20
  /* #6 */ Method = #4 #24
  /* #7 */ Method = #25 #26
  /* #8 */ Method = #27 #28
  /* #9 */ Method = #27 #29
  /* #10 */ Class = #30
  /* #11 */ UTF8 = "s"
  /* #12 */ UTF8 = "Ljava/lang/String;"
  /* #13 */ UTF8 = "<init>"
  /* #14 */ UTF8 = "()V"
  /* #15 */ UTF8 = "Code"
  /* #16 */ UTF8 = "main"
  /* #17 */ UTF8 = "([Ljava/lang/String;)V"
  /* #18 */ UTF8 = "test"
  /* #19 */ UTF8 = "([Ljava/lang/String;)I"
  /* #20 */ NameAndType = #13 #14

  ///////////////////////////////////////////////////////////////////////////////////////
  // Tested string with characters from '\u7FC0' to '\u7FFF' decoded into 3 bytes
  /* #21 */ {x01 x00 xC0 xE7 xBF x80 xE7 xBF x81 xE7 xBF x82 xE7 xBF x83 xE7 xBF x84 xE7 xBF x85 xE7 xBF x86 xE7 xBF x87 xE7 xBF x88 xE7 xBF x89 xE7 xBF x8A xE7 xBF x8B xE7 xBF x8C xE7 xBF x8D xE7 xBF x8E xE7 xBF x8F xE7 xBF x90 xE7 xBF x91 xE7 xBF x92 xE7 xBF x93 xE7 xBF x94 xE7 xBF x95 xE7 xBF x96 xE7 xBF x97 xE7 xBF x98 xE7 xBF x99 xE7 xBF x9A xE7 xBF x9B xE7 xBF x9C xE7 xBF x9D xE7 xBF x9E xE7 xBF x9F xE7 xBF xA0 xE7 xBF xA1 xE7 xBF xA2 xE7 xBF xA3 xE7 xBF xA4 xE7 xBF xA5 xE7 xBF xA6 xE7 xBF xA7 xE7 xBF xA8 xE7 xBF xA9 xE7 xBF xAA xE7 xBF xAB xE7 xBF xAC xE7 xBF xAD xE7 xBF xAE xE7 xBF xAF xE7 xBF xB0 xE7 xBF xB1 xE7 xBF xB2 xE7 xBF xB3 xE7 xBF xB4 xE7 xBF xB5 xE7 xBF xB6 xE7 xBF xB7 xE7 xBF xB8 xE7 xBF xB9 xE7 xBF xBA xE7 xBF xBB xE7 xBF xBC xE7 xBF xBD xE7 xBF xBE xE7 xBF xBF} 
  ///////////////////////////////////////////////////////////////////////////////////////

  /* #22 */ NameAndType = #11 #12
  /* #23 */ UTF8 = "org/apache/harmony/vts/test/vm/jvms/classFile/constantPool/utf8Info/utf8Info07/utf8Info07p"
  /* #24 */ NameAndType = #18 #19
  /* #25 */ Class = #31
  /* #26 */ NameAndType = #32 #33
  /* #27 */ Class = #34
  /* #28 */ NameAndType = #35 #36
  /* #29 */ NameAndType = #37 #38
  /* #30 */ UTF8 = "java/lang/Object"
  /* #31 */ UTF8 = "java/lang/System"
  /* #32 */ UTF8 = "exit"
  /* #33 */ UTF8 = "(I)V"
  /* #34 */ UTF8 = "java/lang/String"
  /* #35 */ UTF8 = "length"
  /* #36 */ UTF8 = "()I"
  /* #37 */ UTF8 = "charAt"
  /* #38 */ UTF8 = "(I)C"
}

access_flags = PUBLIC SUPER  // x21

this_class = #4  // "org/apache/harmony/vts/test/vm/jvms/classFile/constantPool/utf8Info/utf8Info07/utf8Info07p"

super_class = #10  // "java/lang/Object"

interfaces_count = 0

interfaces {
}

fields_count = 1

fields {
  field {
    access_flag = PUBLIC  // x01
    name_index = #11  // "s"
    descriptor_index = #12  // "Ljava/lang/String;"
    attributes_count = 0
  }
}

methods_count = 3

methods {
  method {
    access_flag = PUBLIC  // x01
    name_index = #13  // "<init>"
    descriptor_index = #14  // "()V"
    attributes_count = 1
      attributes {
        attribute Code {
          attribute_name_index = #15  // "Code"
          attribute_length = 23
          max_stack = 2
          max_locals = 1
          code_length = 11
          code asm {
          0:    aload_0
          1:    invokespecial #1  // "java/lang/Object" "<init>" "()V"
          4:    aload_0
          5:    ldc #2
          7:    putfield #3  // "org/apache/harmony/vts/test/vm/jvms/classFile/constantPool/utf8Info/utf8Info07/utf8Info07p" "s" "Ljava/lang/String;"
          10:   return
          }
          exception_table_length = 0
          attributes_count = 0
        }
      }
  }
  method {
    access_flag = PUBLIC STATIC  // x09
    name_index = #16  // "main"
    descriptor_index = #17  // "([Ljava/lang/String;)V"
    attributes_count = 1
      attributes {
        attribute Code {
          attribute_name_index = #15  // "Code"
          attribute_length = 29
          max_stack = 2
          max_locals = 2
          code_length = 17
          code asm {
          0:    new #4  // "org/apache/harmony/vts/test/vm/jvms/classFile/constantPool/utf8Info/utf8Info07/utf8Info07p"
          3:    dup
          4:    invokespecial #5  // "org/apache/harmony/vts/test/vm/jvms/classFile/constantPool/utf8Info/utf8Info07/utf8Info07p" "<init>" "()V"
          7:    astore_1
          8:    aload_1
          9:    aload_0
          10:   invokevirtual #6  // "org/apache/harmony/vts/test/vm/jvms/classFile/constantPool/utf8Info/utf8Info07/utf8Info07p" "test" "([Ljava/lang/String;)I"
          13:   invokestatic #7  // "java/lang/System" "exit" "(I)V"
          16:   return
          }
          exception_table_length = 0
          attributes_count = 0
        }
      }
  }
  method {
    access_flag = PUBLIC  // x01
    name_index = #18  // "test"
    descriptor_index = #19  // "([Ljava/lang/String;)I"
    attributes_count = 1
      attributes {
        attribute Code {
          attribute_name_index = #15  // "Code"
          attribute_length = 51
          max_stack = 3
          max_locals = 4
          code_length = 39
          code asm {
          0:    sipush 32704 // first character '\u7FC0'
          3:    istore_2
          4:    iconst_0
          5:    istore_3
          6:    iload_3
          7:    ldc #2 
          9:    invokevirtual #8  // "java/lang/String" "length" "()I"
          12:   if_icmpge 24
          15:   ldc #2
          17:   iload_3
          18:   invokevirtual #9  // "java/lang/String" "charAt" "(I)C"
          21:   iload_3
          22:   iload_2
          23:   iadd
          24:   if_icmpeq 6
          27:   bipush 105
          29:   ireturn
          30:   iinc 3 1
          33:   goto -27
          36:   bipush 104
          38:   ireturn
          }
          exception_table_length = 0
          attributes_count = 0
        }
      }
  }
}

attributes_count = 0
