/*
    Copyright 2005-2006 The Apache Software Foundation or its licensors, as applicable

    Licensed under the Apache License, Version 2.0 (the "License");
    you may not use this file except in compliance with the License.
    You may obtain a copy of the License at

       http://www.apache.org/licenses/LICENSE-2.0

    Unless required by applicable law or agreed to in writing, software
    distributed under the License is distributed on an "AS IS" BASIS,
    WITHOUT WARRANTIES OR CONDITIONS OF ANY KIND, either express or implied.

    See the License for the specific language governing permissions and
    limitations under the License.
*/
// Ccode file

/**
 * @author: Alexander D. Shipilov
 * @version: $Revision: 1.2 $
 */

magic = xCAFEBABE

minor_version = 0

major_version = 46

constant_pool_count = 21

constant_pool {
  /* #1 */ Method = #4 #16
  /* #2 */ Method = #3 #17
  /* #3 */ Class = #18
  /* #4 */ Class = #19
  /* #5 */ UTF8 = "<init>"
  /* #6 */ UTF8 = "()V"
  /* #7 */ UTF8 = "Code"
  /* #8 */ UTF8 = "LineNumberTable"
  /* #9 */ UTF8 = "myMethod"
  /* #10 */ UTF8 = "()I"
  /* #11 */ UTF8 = "Exceptions"
  /* #12 */ Class = #20
  /* #13 */ UTF8 = "myMethod2"
  /* #14 */ UTF8 = "SourceFile"
  /* #15 */ UTF8 = "attributes02n.java"
  /* #16 */ NameAndType = #5 #6
  /* #17 */ NameAndType = #9 #10
  /* #18 */ UTF8 = "org/apache/harmony/vts/test/vm/jvms/classFile/constraints/static/constraint27/attributes02/attributes02n"
  /* #19 */ UTF8 = "java/lang/Object"
  /* #20 */ UTF8 = "java/lang/LinkageError"
}

access_flags = PUBLIC SUPER  // x21

this_class = #3  // "org/apache/harmony/vts/test/vm/jvms/classFile/constraints/static/constraint27/attributes02/attributes02n"

super_class = #4  // "java/lang/Object"

interfaces_count = 0

interfaces {
}

fields_count = 0

methods_count = 3

methods {
  method {
    access_flag = PUBLIC  // x01
    name_index = #5  // "<init>"
    descriptor_index = #6  // "()V"
    attributes_count = 1
      attributes {
        attribute Code {
          attribute_name_index = #7  // "Code"
          attribute_length = 29
          max_stack = 1
          max_locals = 1
          code_length = 5
          code asm {
          0:	aload_0
          1:	invokespecial #1
          4:	return
          }
          exception_table_length = 0
          attributes_count = 1
            attributes {
              attribute LineNumberTable {
                attribute_name_index = #8  // "LineNumberTable"
                attribute_length = 6
                line_number_table_length = 1
                line_number_table {
                    // start_pc line_number
                    0 3
                }
              }
            }
        }
      }
  }
  method {
    access_flag = PUBLIC  // x01
    name_index = #9  // "myMethod"
    descriptor_index = #10  // "()I"
    attributes_count = 2
      attributes {
        attribute Code {
          attribute_name_index = #7  // "Code"
          attribute_length = 26
          max_stack = 1
          max_locals = 1
          code_length = 2
          code asm {
          0:	iconst_3
          1:	ireturn
          }
          exception_table_length = 0
          attributes_count = 1
            attributes {
              attribute LineNumberTable {
                attribute_name_index = #8  // "LineNumberTable"
                attribute_length = 6
                line_number_table_length = 1
                line_number_table {
                    // start_pc line_number
                    0 5
                }
              }
            }
        }

// Test attribute
        attribute Exceptions {
          attribute_name_index = #11  // "Exceptions"
/////////////////////////////////////////////////////////////////////
          attribute_length = 8        // improper length
/////////////////////////////////////////////////////////////////////
          number_of_exceptions = 1
          exception_index_table {
            #12  // "java/lang/LinkageError"
          }
        }
      }
  }
  method {
    access_flag = PUBLIC  // x01
    name_index = #13  // "myMethod2"
    descriptor_index = #6  // "()V"
    attributes_count = 1
      attributes {
        attribute Code {
          attribute_name_index = #7  // "Code"
          attribute_length = 34
          max_stack = 1
          max_locals = 2
          code_length = 6
          code asm {
          0:	aload_0
          1:	invokevirtual #2
          4:	istore_1
          5:	return
          }
          exception_table_length = 0
          attributes_count = 1
            attributes {
              attribute LineNumberTable {
                attribute_name_index = #8  // "LineNumberTable"
                attribute_length = 10
                line_number_table_length = 2
                line_number_table {
                    // start_pc line_number
                    0 8
                    5 9
                }
              }
            }
        }
      }
  }
}

attributes_count = 1
attributes {
  attribute SourceFile {
    attribute_name_index = #14  // "SourceFile"
    attribute_length = 2
    sourcefile_index = #15  // "attributes02n.java"
  }
}
