/*
    Copyright 2005-2006 The Apache Software Foundation or its licensors, as applicable

    Licensed under the Apache License, Version 2.0 (the "License");
    you may not use this file except in compliance with the License.
    You may obtain a copy of the License at

       http://www.apache.org/licenses/LICENSE-2.0

    Unless required by applicable law or agreed to in writing, software
    distributed under the License is distributed on an "AS IS" BASIS,
    WITHOUT WARRANTIES OR CONDITIONS OF ANY KIND, either express or implied.

    See the License for the specific language governing permissions and
    limitations under the License.
*/
/**
 * Generated ccode file
 * @author VMTT (Virtual Machine Testing Tools)
 * @version 1.0
 * @lastmod: Fri Jun 16 11:38:02 NOVST 2006
 */

magic = xCAFEBABE

minor_version = 0

major_version = 46

constant_pool_count = 22

constant_pool {
  /* #1 */ Method = #5 #14
  /* #2 */ Class = #15
  /* #3 */ Method = #2 #18
  /* #4 */ Class = #19
  /* #5 */ Class = #20
  /* #6 */ UTF8 = "<init>"
  /* #7 */ UTF8 = "()V"
  /* #8 */ UTF8 = "Code"
  /* #9 */ UTF8 = "LineNumberTable"
  /* #10 */ UTF8 = "test"
  /* #11 */ UTF8 = "()V"
  /* #12 */ UTF8 = "SourceFile"
  /* #13 */ UTF8 = "innerClasses03p.ccode"
  /* #14 */ NameAndType = #6 #7
  /* #15 */ UTF8 = "org/apache/harmony/vts/test/vm/jvms/classFile/attributes/innerClasses/innerClasses03/innerClasses03p$1"
  /* #16 */ UTF8 = ""
  /* #17 */ UTF8 = "InnerClasses"
  /* #18 */ NameAndType = #6 #21
  /* #19 */ UTF8 = "org/apache/harmony/vts/test/vm/jvms/classFile/attributes/innerClasses/innerClasses03/innerClasses03p"
  /* #20 */ UTF8 = "java/lang/Object"
  /* #21 */ UTF8 = "(Lorg/apache/harmony/vts/test/vm/jvms/classFile/attributes/innerClasses/innerClasses03/innerClasses03p;)V"
}

access_flags = PUBLIC SUPER  // x21

this_class = #4  

super_class = #5  // "java/lang/Object"

interfaces_count = 0

interfaces {
}

fields_count = 0

methods_count = 2

methods {
  method {
    access_flag = PUBLIC  // x01
    name_index = #6  // "<init>"
    descriptor_index = #7  // "()V"
    attributes_count = 1
      attributes {
        attribute Code {
          attribute_name_index = #8  // "Code"
          attribute_length = 29
          max_stack = 1
          max_locals = 1
          code_length = 5
          code asm {
          0:    aload_0
          1:    invokespecial #1  // "java/lang/Object" "<init>" "()V"
          4:    return
          }
          exception_table_length = 0
          attributes_count = 1
            attributes {
              attribute LineNumberTable {
                attribute_name_index = #9  // "LineNumberTable"
                attribute_length = 6
                line_number_table_length = 1
                line_number_table {
                    // start_pc line_number
                    0 1
                }
              }
            }
        }
      }
  }
  method {
    access_flag = PUBLIC  // x01
    name_index = #10  // "test"
    descriptor_index = #11  // "()V"
    attributes_count = 1
      attributes {
        attribute Code {
          attribute_name_index = #8  // "Code"
          attribute_length = 38
          max_stack = 3
          max_locals = 2
          code_length = 10
          code asm {
          0:    new #2  // "org/apache/harmony/vts/test/vm/jvms/classFile/attributes/innerClasses/innerClasses03/innerClasses03p$1"
          3:    dup
          4:    aload_0
          5:    invokespecial #3  // "innerClasses03p$1" "<init>" "(LinnerClasses03p;)V"
          8:    pop
          9:    return
          }
          exception_table_length = 0
          attributes_count = 1
            attributes {
              attribute LineNumberTable {
                attribute_name_index = #9  // "LineNumberTable"
                attribute_length = 10
                line_number_table_length = 2
                line_number_table {
                    // start_pc line_number
                    0 3
                    9 6
                }
              }
            }
        }
      }
  }
}

attributes_count = 2
attributes {
  attribute SourceFile {
    attribute_name_index = #12  // "SourceFile"
    attribute_length = 2
    sourcefile_index = #13  // "innerClasses03p.ccode"
  }
  attribute InnerClasses {
    attribute_name_index = #17  // "InnerClasses"
    attribute_length = 10 
    number_of_classes = 1
    InnerClass {
        inner_class_info_index = #2  // "innerClasses03p$1"
        outer_class_info_index = #0  // inner class is not a member

        /////////////////////////////////////////////////////////////////////////////////
        inner_name_index = 0  // Tested valid inner_name_index for the anonymous inner class
        /////////////////////////////////////////////////////////////////////////////////

        inner_class_access_flags = 
    }
  }
}
