/*
    Copyright 2005-2006 The Apache Software Foundation or its licensors, as applicable

    Licensed under the Apache License, Version 2.0 (the "License");
    you may not use this file except in compliance with the License.
    You may obtain a copy of the License at

       http://www.apache.org/licenses/LICENSE-2.0

    Unless required by applicable law or agreed to in writing, software
    distributed under the License is distributed on an "AS IS" BASIS,
    WITHOUT WARRANTIES OR CONDITIONS OF ANY KIND, either express or implied.

    See the License for the specific language governing permissions and
    limitations under the License.
*/
/**
 * @author: Alexander V. Esin
 * @version: $Revision: 1.1 $
 */

magic = xCAFEBABE

minor_version = 0

major_version = 49

constant_pool_count = 47

constant_pool {
  /* #1 */ Field = #9 #26
  /* #2 */ Method = #27 #28
  /* #3 */ Class = #14
  /* #4 */ Method = #9 #29
  /* #5 */ Method = #30 #31
  /* #6 */ Class = #32
  /* #7 */ Method = #6 #33
  /* #8 */ Method = #10 #34
  /* #9 */ Class = #36
  /* #10 */ Class = #37
  /* #11 */ UTF8 = "$VALUES"
  /* #12 */ UTF8 = "InnerClass"
  /* #13 */ UTF8 = "InnerClasses"
  /* #14 */ UTF8 = "[Lorg/apache/harmony/vts/test/vm/jvms/classFile/attributes/innerClasses/innerClasses15/innerClasses15$InnerClass;"
  /* #15 */ UTF8 = "values"
  /* #16 */ UTF8 = "()[Lorg/apache/harmony/vts/test/vm/jvms/classFile/attributes/innerClasses/innerClasses15/innerClasses15$InnerClass;"
  /* #17 */ UTF8 = "Code"
  /* #18 */ UTF8 = "valueOf"
  /* #19 */ UTF8 = "(Ljava/lang/String;)Lorg/apache/harmony/vts/test/vm/jvms/classFile/attributes/innerClasses/innerClasses15/innerClasses15$InnerClass;"
  /* #20 */ UTF8 = "<init>"
  /* #21 */ UTF8 = "(Ljava/lang/String;I)V"
  /* #22 */ UTF8 = "Signature"
  /* #23 */ UTF8 = "()V"
  /* #24 */ UTF8 = "<clinit>"
  /* #25 */ UTF8 = "Ljava/lang/Enum<Lorg/apache/harmony/vts/test/vm/jvms/classFile/attributes/innerClasses/innerClasses15/innerClasses15$InnerClass;>;"
  /* #26 */ NameAndType = #11 #14
  /* #27 */ Class = #14
  /* #28 */ NameAndType = #38 #39
  /* #29 */ NameAndType = #40 #41
  /* #30 */ Class = #42
  /* #31 */ NameAndType = #43 #44
  /* #32 */ UTF8 = "java/lang/IllegalArgumentException"
  /* #33 */ NameAndType = #20 #45
  /* #34 */ NameAndType = #20 #21
  /* #35 */ Class = #46
  /* #36 */ UTF8 = "org/apache/harmony/vts/test/vm/jvms/classFile/attributes/innerClasses/innerClasses15/innerClasses15$InnerClass"
  /* #37 */ UTF8 = "java/lang/Enum"
  /* #38 */ UTF8 = "clone"
  /* #39 */ UTF8 = "()Ljava/lang/Object;"
  /* #40 */ UTF8 = "name"
  /* #41 */ UTF8 = "()Ljava/lang/String;"
  /* #42 */ UTF8 = "java/lang/String"
  /* #43 */ UTF8 = "equals"
  /* #44 */ UTF8 = "(Ljava/lang/Object;)Z"
  /* #45 */ UTF8 = "(Ljava/lang/String;)V"
  /* #46 */ UTF8 = "org/apache/harmony/vts/test/vm/jvms/classFile/attributes/innerClasses/innerClasses15/innerClasses15"
}

access_flags = x4031  // PUBLIC FINAL SUPER ENUM 

this_class = #9  // "org/apache/harmony/vts/test/vm/jvms/classFile/attributes/innerClasses/innerClasses15/innerClasses15$InnerClass"

super_class = #10  // "java/lang/Enum"

interfaces_count = 0

interfaces {
}

fields_count = 1

fields {
  field {
    access_flag = x101A  // PRIVATE STATIC FINAL SYNTHETIC 
    name_index = #11  // "$VALUES"
    descriptor_index = #14  // "[Lorg/apache/harmony/vts/test/vm/jvms/classFile/attributes/innerClasses/innerClasses15/innerClasses15$InnerClass;"
    attributes_count = 0
  }
}

methods_count = 4

methods {
  method {
    access_flag = x19  // PUBLIC STATIC FINAL 
    name_index = #15  // "values"
    descriptor_index = #16  // "()[Lorg/apache/harmony/vts/test/vm/jvms/classFile/attributes/innerClasses/innerClasses15/innerClasses15$InnerClass;"
    attributes_count = 1
      attributes {
        attribute Code {
          attribute_name_index = #17  // "Code"
          attribute_length = 22
          max_stack = 1
          max_locals = 0
          code_length = 10
          code asm {
          0:	getstatic #1  // "org/apache/harmony/vts/test/vm/jvms/classFile/attributes/innerClasses/innerClasses15/innerClasses15$InnerClass" "$VALUES" "[Lorg/apache/harmony/vts/test/vm/jvms/classFile/attributes/innerClasses/innerClasses15/innerClasses15$InnerClass;"
          3:	invokevirtual #2  // "[Lorg/apache/harmony/vts/test/vm/jvms/classFile/attributes/innerClasses/innerClasses15/innerClasses15$InnerClass;" "clone" "()Ljava/lang/Object;"
          6:	checkcast #3  // "[Lorg/apache/harmony/vts/test/vm/jvms/classFile/attributes/innerClasses/innerClasses15/innerClasses15$InnerClass;"
          9:	areturn
          }
          exception_table_length = 0
          attributes_count = 0
        }
      }
  }
  method {
    access_flag = x09  // PUBLIC STATIC 
    name_index = #18  // "valueOf"
    descriptor_index = #19  // "(Ljava/lang/String;)Lorg/apache/harmony/vts/test/vm/jvms/classFile/attributes/innerClasses/innerClasses15/innerClasses15$InnerClass;"
    attributes_count = 1
      attributes {
        attribute Code {
          attribute_name_index = #17  // "Code"
          attribute_length = 61
          max_stack = 3
          max_locals = 5
          code_length = 49
          code asm {
          0:	getstatic #1  // "org/apache/harmony/vts/test/vm/jvms/classFile/attributes/innerClasses/innerClasses15/innerClasses15$InnerClass" "$VALUES" "[Lorg/apache/harmony/vts/test/vm/jvms/classFile/attributes/innerClasses/innerClasses15/innerClasses15$InnerClass;"
          3:	astore_1
          4:	aload_1
          5:	arraylength
          6:	istore_2
          7:	iconst_0
          8:	istore_3
          9:	iload_3
          10:	iload_2
          11:	if_icmpge 29
          14:	aload_1
          15:	iload_3
          16:	aaload
          17:	astore 4
          19:	aload 4
          21:	invokevirtual #4  // "org/apache/harmony/vts/test/vm/jvms/classFile/attributes/innerClasses/innerClasses15/innerClasses15$InnerClass" "name" "()Ljava/lang/String;"
          24:	aload_0
          25:	invokevirtual #5  // "java/lang/String" "equals" "(Ljava/lang/Object;)Z"
          28:	ifeq 6
          31:	aload 4
          33:	areturn
          34:	iinc 3 1
          37:	goto -28
          40:	new #6  // "java/lang/IllegalArgumentException"
          43:	dup
          44:	aload_0
          45:	invokespecial #7  // "java/lang/IllegalArgumentException" "<init>" "(Ljava/lang/String;)V"
          48:	athrow
          }
          exception_table_length = 0
          attributes_count = 0
        }
      }
  }
  method {
    access_flag = x02  // PRIVATE 
    name_index = #20  // "<init>"
    descriptor_index = #21  // "(Ljava/lang/String;I)V"
    attributes_count = 2
      attributes {
        attribute Code {
          attribute_name_index = #17  // "Code"
          attribute_length = 19
          max_stack = 3
          max_locals = 3
          code_length = 7
          code asm {
          0:	aload_0
          1:	aload_1
          2:	iload_2
          3:	invokespecial #8  // "java/lang/Enum" "<init>" "(Ljava/lang/String;I)V"
          6:	return
          }
          exception_table_length = 0
          attributes_count = 0
        }
        attribute Signature {
          attribute_name_index = #22  // "Signature"
          attribute_length = 2
          signature_index = #23  // "()V"
        }
      }
  }
  method {
    access_flag = x08  // STATIC 
    name_index = #24  // "<clinit>"
    descriptor_index = #23  // "()V"
    attributes_count = 1
      attributes {
        attribute Code {
          attribute_name_index = #17  // "Code"
          attribute_length = 20
          max_stack = 1
          max_locals = 0
          code_length = 8
          code asm {
          0:	iconst_0
          1:	anewarray #9  // "org/apache/harmony/vts/test/vm/jvms/classFile/attributes/innerClasses/innerClasses15/innerClasses15$InnerClass"
          4:	putstatic #1  // "org/apache/harmony/vts/test/vm/jvms/classFile/attributes/innerClasses/innerClasses15/innerClasses15$InnerClass" "$VALUES" "[Lorg/apache/harmony/vts/test/vm/jvms/classFile/attributes/innerClasses/innerClasses15/innerClasses15$InnerClass;"
          7:	return
          }
          exception_table_length = 0
          attributes_count = 0
        }
      }
  }
}

attributes_count = 2
attributes {
  attribute Signature {
    attribute_name_index = #22  // "Signature"
    attribute_length = 2
    signature_index = #25  // "Ljava/lang/Enum<Lorg/apache/harmony/vts/test/vm/jvms/classFile/attributes/innerClasses/innerClasses15/innerClasses15$InnerClass;>;"
  }
  attribute InnerClasses {
    attribute_name_index = #13  // "InnerClasses"
    attribute_length = 10
    number_of_classes = 1
    InnerClass {
        inner_class_info_index = #9  // "org/apache/harmony/vts/test/vm/jvms/classFile/attributes/innerClasses/innerClasses15/innerClasses15$InnerClass"
        outer_class_info_index = #35  // "org/apache/harmony/vts/test/vm/jvms/classFile/attributes/innerClasses/innerClasses15/innerClasses15"
        inner_name_index = #12  // "InnerClass"
        inner_class_access_flags = x4019  // PUBLIC STATIC FINAL ENUM 
    }
  }
}
